BAOSNetLib_python-1.2.0.dist-info/DESCRIPTION.rst
BAOSNetLib_python-1.2.0.dist-info/METADATA
BAOSNetLib_python-1.2.0.dist-info/RECORD
BAOSNetLib_python-1.2.0.dist-info/WHEEL
BAOSNetLib_python-1.2.0.dist-info/metadata.json
BAOSNetLib_python-1.2.0.dist-info/top_level.txt
Baos/BaosNodeImpl.py
Baos/ZMQRPCClient.py
Baos/ZMQRPCServer.py
Baos/__init__.py
Baos/msg_pb2.py
Baos/multicast.py
